xmanage/__init__.py
xmanage/attribute.py
xmanage/systemd/__init__.py
xmanage/systemd/path.py
xmanage/systemd/service.py
xmanage/systemd/unit.py
xmanage/xsystem/__init__.py
xmanage/xsystem/path.py
xmanage-0.7.2.dist-info/LICENSE
xmanage-0.7.2.dist-info/METADATA
xmanage-0.7.2.dist-info/WHEEL
xmanage-0.7.2.dist-info/entry_points.txt
xmanage-0.7.2.dist-info/top_level.txt
xmanage-0.7.2.dist-info/zip-safe
xmanage-0.7.2.dist-info/RECORD
