Metadata-Version: 2.1
Name: xmanage
Version: 0.7.2
Summary: System and service management tool
Home-page: https://github.com/bondbox/xmanage/
Author: Mingzhe Zou
Author-email: zoumingzhe@outlook.com
License: GPLv2
Project-URL: Source Code, https://github.com/bondbox/xmanage/
Project-URL: Bug Tracker, https://github.com/bondbox/xmanage/issues
Project-URL: Documentation, https://github.com/bondbox/xmanage/
Platform: any
Classifier: Programming Language :: Python
Classifier: Programming Language :: Python :: 3
Requires-Python: >=3.8
License-File: LICENSE
Requires-Dist: xkits-command >=0.5
Requires-Dist: xkits-lib >=0.4
Requires-Dist: tabulate
